birdsongrec/__about__.py
birdsongrec/__init__.py
birdsongrec/birdsongrec.py
birdsong_recognition_dataset-0.3.2.post1.dist-info/LICENSE
birdsong_recognition_dataset-0.3.2.post1.dist-info/WHEEL
birdsong_recognition_dataset-0.3.2.post1.dist-info/METADATA
birdsong_recognition_dataset-0.3.2.post1.dist-info/RECORD
