Metadata-Version: 2.1
Name: birdsong-recognition-dataset
Version: 0.3.2.post1
Summary: Functions for working with this data repository: https://figshare.com/articles/BirdsongRecognition/3470165
Author-email: David Nicholson <nickledave@users.noreply.github.com>
Requires-Python: >=3.8
Classifier: License :: OSI Approved :: BSD License
Classifier: Development Status :: 5 - Production/Stable
Classifier: Programming Language :: Python
Classifier: Programming Language :: Python :: 3
Classifier: Programming Language :: Python :: 3.8
Classifier: Programming Language :: Python :: 3.9
Classifier: Programming Language :: Python :: 3.10
Classifier: Programming Language :: Python :: Implementation :: CPython
Requires-Dist: numpy >=1.18.1
Requires-Dist: pytest >=6.2.2 ; extra == "test"
Project-URL: Source, https://github.com/NickleDave/birdsong-recognition-dataset
Provides-Extra: test
